[
  {
    "featureType": "administrative.country",
    "elementType": "geometry.stroke",
    "stylers": [
      {
        "color": "#485650"
      }
    ]
  },
  {
    "featureType": "administrative.province",
    "elementType": "geometry.stroke",
    "stylers": [
      {
        "color": "#485650"
      },
      {
        "visibility": "on"
      }
    ]
  },
  {
    "featureType": "administrative.province",
    "elementType": "labels.text",
    "stylers": [
      {
        "color": "#485650"
      },
      {
        "visibility": "on"
      }
    ]
  },
  {
    "featureType": "administrative.province",
    "elementType": "labels.text.fill",
    "stylers": [
      {
        "color": "#485650"
      },
      {
        "visibility": "on"
      }
    ]
  },
  {
    "featureType": "administrative.province",
    "elementType": "labels.text.stroke",
    "stylers": [
      {
        "visibility": "off"
      }
    ]
  },
  {
    "featureType": "road.highway",
    "elementType": "geometry.fill",
    "stylers": [
      {
        "color": "#ffeb3b"
      }
    ]
  },
  {
    "featureType": "road.highway.controlled_access",
    "elementType": "geometry.fill",
    "stylers": [
      {
        "visibility": "on"
      }
    ]
  }
]